robola/__init__.py
robola/cli.py
robola/server.py
robola/handlers/__init__.py
robola/handlers/model_data.py
robola/handlers/model_save.py
robola/handlers/simulation_runtime.py
robola-0.2.4.dist-info/METADATA
robola-0.2.4.dist-info/WHEEL
robola-0.2.4.dist-info/entry_points.txt
robola-0.2.4.dist-info/licenses/LICENSE
robola-0.2.4.dist-info/RECORD
