Metadata-Version: 2.4
Name: robola
Version: 0.2.4
Summary: Robola MJCF Editor Local Bridge - Local Python Library for MuJoCo and Online Web mjcf editing
Project-URL: Homepage, https://www.robolaweb.com
Project-URL: Repository, https://github.com/robola-dev/robola
Project-URL: Documentation, https://github.com/robola-dev/robola#readme
Project-URL: Issues, https://github.com/robola-dev/robola/issues
Author-email: Robola Team <robolaweb@foxmail.com>
License: MIT
License-File: LICENSE
Keywords: editor,mjcf,mujoco,robotics,simulation
Classifier: Development Status :: 3 - Alpha
Classifier: Intended Audience :: Developers
Classifier: Intended Audience :: Science/Research
Classifier: License :: OSI Approved :: MIT License
Classifier: Programming Language :: Python :: 3
Classifier: Programming Language :: Python :: 3.10
Classifier: Programming Language :: Python :: 3.11
Classifier: Programming Language :: Python :: 3.12
Classifier: Topic :: Scientific/Engineering
Requires-Python: >=3.10
Requires-Dist: fastapi>=0.100.0
Requires-Dist: mujoco>=3.3.0
Requires-Dist: numpy>=1.20.0
Requires-Dist: scipy>=1.7.0
Requires-Dist: trimesh>=3.0.0
Requires-Dist: uvicorn[standard]>=0.20.0
Requires-Dist: websockets>=11.0
Provides-Extra: dev
Requires-Dist: pytest-asyncio>=0.21.0; extra == 'dev'
Requires-Dist: pytest>=7.0.0; extra == 'dev'
